jupyterlab_hide_code/__init__.py
jupyterlab_hide_code/_version.py
jupyterlab_hide_code-4.0.0.data/data/share/jupyter/labextensions/jupyterlab_hide_code/build_log.json
jupyterlab_hide_code-4.0.0.data/data/share/jupyter/labextensions/jupyterlab_hide_code/package.json
jupyterlab_hide_code-4.0.0.data/data/share/jupyter/labextensions/jupyterlab_hide_code/schemas/jupyterlab_hide_code/package.json.orig
jupyterlab_hide_code-4.0.0.data/data/share/jupyter/labextensions/jupyterlab_hide_code/schemas/jupyterlab_hide_code/plugin.json
jupyterlab_hide_code-4.0.0.data/data/share/jupyter/labextensions/jupyterlab_hide_code/static/lib_index_js.982c91ab12ef33ba33d4.js
jupyterlab_hide_code-4.0.0.data/data/share/jupyter/labextensions/jupyterlab_hide_code/static/lib_index_js.982c91ab12ef33ba33d4.js.map
jupyterlab_hide_code-4.0.0.data/data/share/jupyter/labextensions/jupyterlab_hide_code/static/remoteEntry.3b2ac13a839eb96bd9f4.js
jupyterlab_hide_code-4.0.0.data/data/share/jupyter/labextensions/jupyterlab_hide_code/static/remoteEntry.3b2ac13a839eb96bd9f4.js.map
jupyterlab_hide_code-4.0.0.data/data/share/jupyter/labextensions/jupyterlab_hide_code/static/style.js
jupyterlab_hide_code-4.0.0.data/data/share/jupyter/labextensions/jupyterlab_hide_code/static/style_index_js.aae21a5a3c7d2c98990c.js
jupyterlab_hide_code-4.0.0.data/data/share/jupyter/labextensions/jupyterlab_hide_code/static/style_index_js.aae21a5a3c7d2c98990c.js.map
jupyterlab_hide_code-4.0.0.data/data/share/jupyter/labextensions/jupyterlab_hide_code/install.json
jupyterlab_hide_code-4.0.0.dist-info/METADATA
jupyterlab_hide_code-4.0.0.dist-info/WHEEL
jupyterlab_hide_code-4.0.0.dist-info/licenses/LICENSE
jupyterlab_hide_code-4.0.0.dist-info/RECORD
