Metadata-Version: 2.3
Name: jupyterlab_hide_code
Version: 4.0.0
Dynamic: Keywords
Summary: A button in JupyterLab to run the code cells and then to hide the code cells.
Project-URL: Homepage, https://github.com/osscar-org/jupyterlab-hide-code
Project-URL: Bug Tracker, https://github.com/osscar-org/jupyterlab-hide-code/issues
Project-URL: Repository, https://github.com/osscar-org/jupyterlab-hide-code.git
Author-email: Dou Du <dou.du@icloud.com>
License: BSD 3-Clause License
License-File: LICENSE
Classifier: Framework :: Jupyter
Classifier: Framework :: Jupyter :: JupyterLab
Classifier: Framework :: Jupyter :: JupyterLab :: 4
Classifier: Framework :: Jupyter :: JupyterLab :: Extensions
Classifier: Framework :: Jupyter :: JupyterLab :: Extensions :: Prebuilt
Classifier: License :: OSI Approved :: BSD License
Classifier: Programming Language :: Python
Classifier: Programming Language :: Python :: 3
Classifier: Programming Language :: Python :: 3.8
Classifier: Programming Language :: Python :: 3.9
Classifier: Programming Language :: Python :: 3.10
Classifier: Programming Language :: Python :: 3.11
Requires-Python: >=3.8
